##判断一个数组中最大数和最小数是否相等，不相等则加起来
public class Hello {

    public static void main(String[] args) {
        int[] s1 = {1, 2, 3, 4, 5, 6, 7, 8};
        int max = 0;
        int min = 0;

        for (int i = 0; i < s1.length; i++) {
            max = Math.max(max, s1[i]);
            min = Math.min(min, s1[i]);
        }

        int total = 0;
        if (min != max) {
            total = add(min, max);
        }

        System.out.println(total);
    }

    private static int add(int s1, int s2) {
        return s1 + s2;
    }

}


## 字节码指令
Compiled from "Hello.java"
public class com.mhxs.blog.test.Hello {
  public com.mhxs.blog.test.Hello();
    Code:
       0: aload_0
       1: invokespecial #1                  // Method java/lang/Object."<init>":()V
       4: return

  public static void main(java.lang.String[]);
    Code:
       0: bipush        8
       2: newarray       int
       4: dup
       5: iconst_0
       6: iconst_1
       7: iastore
       8: dup
       9: iconst_1
      10: iconst_2
      11: iastore
      12: dup
      13: iconst_2
      14: iconst_3
      15: iastore
      16: dup
      17: iconst_3
      18: iconst_4
      19: iastore
      20: dup
      21: iconst_4
      22: iconst_5
      23: iastore
      24: dup
      25: iconst_5
      26: bipush        6
      28: iastore
      29: dup
      30: bipush        6
      32: bipush        7
      34: iastore
      35: dup
      36: bipush        7
      38: bipush        8
      40: iastore
      41: astore_1
      42: iconst_0
      43: istore_2
      44: iconst_0
      45: istore_3
      46: iconst_0
      47: istore        4
      49: iload         4
      51: aload_1
      52: arraylength
      53: if_icmpge     80
      56: iload_2
      57: aload_1
      58: iload         4
      60: iaload
      61: invokestatic  #2                  // Method java/lang/Math.max:(II)I
      64: istore_2
      65: iload_3
      66: aload_1
      67: iload         4
      69: iaload
      70: invokestatic  #3                  // Method java/lang/Math.min:(II)I
      73: istore_3
      74: iinc          4, 1
      77: goto          49
      80: iconst_0
      81: istore        4
      83: iload_3
      84: iload_2
      85: if_icmpeq     95
      88: iload_3
      89: iload_2
      90: invokestatic  #4                  // Method add:(II)I
      93: istore        4
      95: getstatic     #5                  // Field java/lang/System.out:Ljava/io/PrintStream;
      98: iload         4
     100: invokevirtual #6                  // Method java/io/PrintStream.println:(I)V
     103: return
}



分析如下从第11行开始
1 将8入栈
2 先从栈弹出获取栈顶的值，获取到8，然后创建8个int类型元素的数组对象，并把该数组对象的引用值压入栈顶
3 复制栈顶的数组对象引用值 并将复制值压入栈顶
4 将int类型常量0压入栈，该值为数组下标
5 将int类型常量1压入栈，该值为要存入数组的元素值
6 从操作数栈弹出元素值（1）、数组下标（0）、数组的对象引用，并将元素值存入数组对应的下标中
7 复制数组的对象引用，并将其压栈
8 将int类型常量1压入栈，该值为数组下标
9 将int类型常量2压入栈，该值为要存入数组的元素值
10 从操作数栈弹出元素值（2）、数组下标（1）、数组的对象引用，并将元素值存入数组对应的下标中
11 复制栈顶的数组对象引用值 并将复制值压入栈顶
.... 重复到35行
35 将栈顶的数组对象引用 保存到槽位为1的局部变量中，也就是将数组引用赋值给局部变量s1
36 将int类型常量0压入栈
37 将0存入局部变量2  --- max
38 将int类型常量0压入栈
39 将0存入局部变量3  ---min
40 将int类型常量0压入栈
41 将0存入局部变量4  --- i
42 从局部变量4中装载int类型值0
43 从局部变量1中装载引用类型值(数组引用)
44 获取数组长度
45 如果大于等于数组长度就跳出循环
46 装载局部变量2的数值0
47 获取数组引用
48 装载局部变量4的数值0
49 获取数组第0（局部变量4）位元素
50 invokestatic 调用Math.max
51 将结果值放入局部变量2
52 装载局部变量3的数值0
53 获取数组引用
54 装载局部变量4的数值0
55 获取数组第0（局部变量4）位元素
56 invokestatic 调用Math.min
57 将结果值放入局部变量3
58 局部变量4（i）自增
59 无条件跳转 偏移量49的位置
60 0入栈
61 将0存入局部变量4
62 从局部变量3中装载int类型值
63 从局部变量2中装载int类型值
65 根据条件判断是否转移到偏移量95，这里条件就是最大值和最小值是否相等
66 从局部变量3中装载int类型值
67 从局部变量2中装载int类型值
68 invokestatic 执行add方法
69 istore 将结果存入局部变量4
70 打印结果
71 从局部变量4中装载int类型值
72 从方法中返回，返回值为void

